README.rst
setup.py
gogpy/__init__.py
gogpy/gogpy.py
gogpy.egg-info/PKG-INFO
gogpy.egg-info/SOURCES.txt
gogpy.egg-info/dependency_links.txt
gogpy.egg-info/requires.txt
gogpy.egg-info/top_level.txt