Metadata-Version: 1.1
Name: gogpy
Version: 0.0.2
Summary: use gog visualization system from Python
Home-page: https://github.com/ajschumacher/gogpy
Author: Aaron Schumacher
Author-email: ajschumacher@gmail.com
License: MIT
Download-URL: https://github.com/ajschumacher/gogpy/tarball/0.0.2
Platform: UNKNOWN
